arcade_core/__init__.py
arcade_core/annotations.py
arcade_core/auth.py
arcade_core/auth_tokens.py
arcade_core/catalog.py
arcade_core/config.py
arcade_core/config_model.py
arcade_core/constants.py
arcade_core/context.py
arcade_core/discovery.py
arcade_core/errors.py
arcade_core/executor.py
arcade_core/output.py
arcade_core/parse.py
arcade_core/py.typed
arcade_core/schema.py
arcade_core/toolkit.py
arcade_core/utils.py
arcade_core/version.py
arcade_core/converters/__init__.py
arcade_core/converters/anthropic.py
arcade_core/converters/openai.py
arcade_core/converters/utils.py
arcade_core/network/__init__.py
arcade_core/network/org_transport.py
arcade_core/usage/__init__.py
arcade_core/usage/__main__.py
arcade_core/usage/constants.py
arcade_core/usage/identity.py
arcade_core/usage/usage_service.py
arcade_core/usage/utils.py
arcade_core-4.2.2.dist-info/METADATA
arcade_core-4.2.2.dist-info/WHEEL
arcade_core-4.2.2.dist-info/RECORD
