Metadata-Version: 2.4
Name: arcade-core
Version: 4.2.2
Summary: Arcade Core - Core library for Arcade platform
Author-email: Arcade <dev@arcade.dev>
License: MIT
Classifier: Development Status :: 5 - Production/Stable
Classifier: Intended Audience :: Developers
Classifier: License :: OSI Approved :: MIT License
Classifier: Programming Language :: Python :: 3
Classifier: Programming Language :: Python :: 3.10
Classifier: Programming Language :: Python :: 3.11
Classifier: Programming Language :: Python :: 3.12
Classifier: Programming Language :: Python :: 3.13
Requires-Python: >=3.10
Requires-Dist: httpx>=0.27.0
Requires-Dist: loguru>=0.7.0
Requires-Dist: packaging>=24.1
Requires-Dist: portalocker>=2.10.0
Requires-Dist: posthog<7.0.0,>=6.7.6
Requires-Dist: pydantic>=2.7.0
Requires-Dist: pyjwt>=2.8.0
Requires-Dist: pyyaml>=6.0
Requires-Dist: toml>=0.10.2
Requires-Dist: types-python-dateutil==2.9.0.20241003
Requires-Dist: types-pytz==2024.2.0.20241003
Requires-Dist: types-toml==0.10.8.20240310
Provides-Extra: dev
Requires-Dist: mypy>=1.5.1; extra == 'dev'
Requires-Dist: pre-commit>=3.4.0; extra == 'dev'
Requires-Dist: pytest-asyncio>=0.23.7; extra == 'dev'
Requires-Dist: pytest-cov>=4.0.0; extra == 'dev'
Requires-Dist: pytest>=8.1.2; extra == 'dev'
Requires-Dist: types-python-dateutil>=2.8.2; extra == 'dev'
Requires-Dist: types-pytz>=2024.1; extra == 'dev'
Requires-Dist: types-pyyaml>=6.0.0; extra == 'dev'
